lib/__init__.py
lib/diff.py
lib/io.py
lib/merge.py
lib/norm.py
lib/parsers.py
lib/stats.py
nretools-0.0.1.data/scripts/nretools
nretools-0.0.1.dist-info/DESCRIPTION.rst
nretools-0.0.1.dist-info/METADATA
nretools-0.0.1.dist-info/RECORD
nretools-0.0.1.dist-info/WHEEL
nretools-0.0.1.dist-info/metadata.json
nretools-0.0.1.dist-info/top_level.txt
