Metadata-Version: 2.0
Name: nretools
Version: 0.0.1
Summary: A software package for finding differential A-to-I editing.
Home-page: UNKNOWN
Author: Tyler Weirick
Author-email: tyler.weirick@gmail.com
License: MIT
Platform: any
Requires-Dist: intervaltree (>=2.1.0)
